<?xml version="1.0" encoding="UTF-8"?><record_update>
    <sys_choice action="INSERT_OR_UPDATE" field="u_what_needed" table="var__m_sys_decision_input_edc4739edb185050792cf6dfbf9619aa" version="3">
        <sys_choice action="INSERT_OR_UPDATE">
            <dependent_value/>
            <element>u_what_needed</element>
            <hint/>
            <inactive>false</inactive>
            <label>Facilities 1</label>
            <language>en</language>
            <name>var__m_sys_decision_input_edc4739edb185050792cf6dfbf9619aa</name>
            <sequence/>
            <sys_created_by>admin</sys_created_by>
            <sys_created_on>2020-04-23 11:09:53</sys_created_on>
            <sys_domain>global</sys_domain>
            <sys_domain_path>/</sys_domain_path>
            <sys_id>9cc6b312db585050792cf6dfbf961903</sys_id>
            <sys_mod_count>0</sys_mod_count>
            <sys_updated_by>admin</sys_updated_by>
            <sys_updated_on>2020-04-23 11:09:53</sys_updated_on>
            <value>facilities 1</value>
        </sys_choice>
        <sys_choice action="INSERT_OR_UPDATE">
            <dependent_value/>
            <element>u_what_needed</element>
            <hint/>
            <inactive>false</inactive>
            <label>Facilities 2</label>
            <language>en</language>
            <name>var__m_sys_decision_input_edc4739edb185050792cf6dfbf9619aa</name>
            <sequence/>
            <sys_created_by>admin</sys_created_by>
            <sys_created_on>2020-04-23 11:10:23</sys_created_on>
            <sys_domain>global</sys_domain>
            <sys_domain_path>/</sys_domain_path>
            <sys_id>67c6b7dedb185050792cf6dfbf961985</sys_id>
            <sys_mod_count>0</sys_mod_count>
            <sys_updated_by>admin</sys_updated_by>
            <sys_updated_on>2020-04-23 11:10:23</sys_updated_on>
            <value>facilities 2</value>
        </sys_choice>
        <sys_choice action="INSERT_OR_UPDATE">
            <dependent_value/>
            <element>u_what_needed</element>
            <hint/>
            <inactive>false</inactive>
            <label>Human Resources 1</label>
            <language>en</language>
            <name>var__m_sys_decision_input_edc4739edb185050792cf6dfbf9619aa</name>
            <sequence/>
            <sys_created_by>admin</sys_created_by>
            <sys_created_on>2020-04-23 11:10:51</sys_created_on>
            <sys_domain>global</sys_domain>
            <sys_domain_path>/</sys_domain_path>
            <sys_id>14f6b7dedb185050792cf6dfbf961988</sys_id>
            <sys_mod_count>0</sys_mod_count>
            <sys_updated_by>admin</sys_updated_by>
            <sys_updated_on>2020-04-23 11:10:51</sys_updated_on>
            <value>hr1</value>
        </sys_choice>
        <sys_choice action="INSERT_OR_UPDATE">
            <dependent_value/>
            <element>u_what_needed</element>
            <hint/>
            <inactive>false</inactive>
            <label>Human Resources 2</label>
            <language>en</language>
            <name>var__m_sys_decision_input_edc4739edb185050792cf6dfbf9619aa</name>
            <sequence/>
            <sys_created_by>admin</sys_created_by>
            <sys_created_on>2020-04-23 11:11:22</sys_created_on>
            <sys_domain>global</sys_domain>
            <sys_domain_path>/</sys_domain_path>
            <sys_id>3a07b712db585050792cf6dfbf96193e</sys_id>
            <sys_mod_count>0</sys_mod_count>
            <sys_updated_by>admin</sys_updated_by>
            <sys_updated_on>2020-04-23 11:11:22</sys_updated_on>
            <value>hr2</value>
        </sys_choice>
        <sys_choice action="INSERT_OR_UPDATE">
            <dependent_value/>
            <element>u_what_needed</element>
            <hint/>
            <inactive>false</inactive>
            <label>Legal 1</label>
            <language>en</language>
            <name>var__m_sys_decision_input_edc4739edb185050792cf6dfbf9619aa</name>
            <sequence/>
            <sys_created_by>admin</sys_created_by>
            <sys_created_on>2020-04-23 11:09:18</sys_created_on>
            <sys_domain>global</sys_domain>
            <sys_domain_path>/</sys_domain_path>
            <sys_id>6496ffdedb185050792cf6dfbf961908</sys_id>
            <sys_mod_count>0</sys_mod_count>
            <sys_updated_by>admin</sys_updated_by>
            <sys_updated_on>2020-04-23 11:09:18</sys_updated_on>
            <value>legal 1</value>
        </sys_choice>
        <sys_choice action="INSERT_OR_UPDATE">
            <dependent_value/>
            <element>u_what_needed</element>
            <hint/>
            <inactive>false</inactive>
            <label>Legal 2</label>
            <language>en</language>
            <name>var__m_sys_decision_input_edc4739edb185050792cf6dfbf9619aa</name>
            <sequence/>
            <sys_created_by>admin</sys_created_by>
            <sys_created_on>2020-04-23 11:09:31</sys_created_on>
            <sys_domain>global</sys_domain>
            <sys_domain_path>/</sys_domain_path>
            <sys_id>c3a63fdedb185050792cf6dfbf961919</sys_id>
            <sys_mod_count>0</sys_mod_count>
            <sys_updated_by>admin</sys_updated_by>
            <sys_updated_on>2020-04-23 11:09:31</sys_updated_on>
            <value>legal 2</value>
        </sys_choice>
        <sys_choice action="INSERT_OR_UPDATE">
            <dependent_value/>
            <element>u_what_needed</element>
            <hint/>
            <inactive>false</inactive>
            <label>Other</label>
            <language>en</language>
            <name>var__m_sys_decision_input_edc4739edb185050792cf6dfbf9619aa</name>
            <sequence/>
            <sys_created_by>admin</sys_created_by>
            <sys_created_on>2020-04-23 11:11:47</sys_created_on>
            <sys_domain>global</sys_domain>
            <sys_domain_path>/</sys_domain_path>
            <sys_id>7b277312db585050792cf6dfbf961967</sys_id>
            <sys_mod_count>0</sys_mod_count>
            <sys_updated_by>admin</sys_updated_by>
            <sys_updated_on>2020-04-23 11:11:47</sys_updated_on>
            <value>other</value>
        </sys_choice>
        <sys_choice_set action="INSERT_OR_UPDATE">
            <element>u_what_needed</element>
            <name>var__m_sys_decision_input_edc4739edb185050792cf6dfbf9619aa</name>
            <sys_class_name>sys_choice_set</sys_class_name>
            <sys_created_by>admin</sys_created_by>
            <sys_created_on>2020-04-23 11:09:18</sys_created_on>
            <sys_customer_update>false</sys_customer_update>
            <sys_id>42a6b7dedb185050792cf6dfbf961957</sys_id>
            <sys_mod_count>0</sys_mod_count>
            <sys_name>u_what_needed</sys_name>
            <sys_package display_value="NeedIt" source="x_58872_needit">6ead8e780f603200cd674f8ce1050ed1</sys_package>
            <sys_policy/>
            <sys_replace_on_upgrade>false</sys_replace_on_upgrade>
            <sys_scope display_value="NeedIt">6ead8e780f603200cd674f8ce1050ed1</sys_scope>
            <sys_update_name>sys_choice_var__m_sys_decision_input_edc4739edb185050792cf6dfbf9619aa_u_what_needed</sys_update_name>
            <sys_updated_by>admin</sys_updated_by>
            <sys_updated_on>2020-04-23 11:09:18</sys_updated_on>
        </sys_choice_set>
    </sys_choice>
</record_update>
